pyepo/EPO.py
pyepo/__init__.py
pyepo/utlis.py
pyepo/data/__init__.py
pyepo/data/dataset.py
pyepo/data/knapsack.py
pyepo/data/portfolio.py
pyepo/data/shortestpath.py
pyepo/data/tsp.py
pyepo/func/__init__.py
pyepo/func/abcmodule.py
pyepo/func/blackbox.py
pyepo/func/contrastive.py
pyepo/func/perturbed.py
pyepo/func/rank.py
pyepo/func/surrogate.py
pyepo/func/utlis.py
pyepo/metric/__init__.py
pyepo/metric/metrics.py
pyepo/metric/mse.py
pyepo/metric/regret.py
pyepo/metric/unambregret.py
pyepo/model/__init__.py
pyepo/model/opt.py
pyepo/model/copt/__init__.py
pyepo/model/copt/coptmodel.py
pyepo/model/copt/knapsack.py
pyepo/model/copt/shortestpath.py
pyepo/model/grb/__init__.py
pyepo/model/grb/grbmodel.py
pyepo/model/grb/knapsack.py
pyepo/model/grb/portfolio.py
pyepo/model/grb/shortestpath.py
pyepo/model/grb/tsp.py
pyepo/model/mpax/__init__.py
pyepo/model/mpax/knapsack.py
pyepo/model/mpax/mpaxmodel.py
pyepo/model/mpax/shortestpath.py
pyepo/model/omo/__init__.py
pyepo/model/omo/knapsack.py
pyepo/model/omo/omomodel.py
pyepo/model/omo/shortestpath.py
pyepo/twostage/__init__.py
pyepo/twostage/autosklearnpred.py
pyepo/twostage/sklearnpred.py
pyepo-1.0.2.dist-info/METADATA
pyepo-1.0.2.dist-info/WHEEL
pyepo-1.0.2.dist-info/top_level.txt
pyepo-1.0.2.dist-info/RECORD
