Metadata-Version: 2.4
Name: pyepo
Version: 1.0.2
Summary: PyTorch-based End-to-End Predict-then-Optimize Tool
Home-page: https://github.com/khalil-research/PyEPO
Author: Bo Tang
Author-email: bolucas.tang@mail.utoronto.ca
Classifier: Programming Language :: Python :: 3
Classifier: Operating System :: OS Independent
Requires-Python: >=3.7
Requires-Dist: numpy
Requires-Dist: scipy
Requires-Dist: pathos
Requires-Dist: tqdm
Requires-Dist: configspace
Requires-Dist: scikit_learn
Requires-Dist: torch>=1.13.1
Provides-Extra: pyomo
Requires-Dist: pyomo>=6.1.2; extra == "pyomo"
Provides-Extra: gurobi
Requires-Dist: gurobipy>=9.1.2; extra == "gurobi"
Provides-Extra: all
Requires-Dist: pyomo>=6.1.2; extra == "all"
Requires-Dist: gurobipy>=9.1.2; extra == "all"
Dynamic: author
Dynamic: author-email
Dynamic: classifier
Dynamic: description
Dynamic: description-content-type
Dynamic: home-page
Dynamic: provides-extra
Dynamic: requires-dist
Dynamic: requires-python
Dynamic: summary
